mayaai/__init__.py
mayaai-0.1.0.dist-info/licenses/LICENSE.txt
mayaai-0.1.0.dist-info/METADATA
mayaai-0.1.0.dist-info/WHEEL
mayaai-0.1.0.dist-info/top_level.txt
mayaai-0.1.0.dist-info/RECORD
