Metadata-Version: 2.4
Name: mayaai
Version: 0.1.0
Summary: Git Artificial Intelligence
Author-email: Athira <athira.srivani@gmail.com>
Classifier: Programming Language :: Python :: 3
Classifier: License :: OSI Approved :: Apache Software License
Classifier: Operating System :: OS Independent
Requires-Python: >=3.9
License-File: LICENSE.txt
Dynamic: license-file
Dynamic: requires-python
